cryptojs/__init__.py
cryptojs/crypto.py
encryptJS-0.0.2.dist-info/METADATA
encryptJS-0.0.2.dist-info/WHEEL
encryptJS-0.0.2.dist-info/top_level.txt
encryptJS-0.0.2.dist-info/RECORD
