Metadata-Version: 2.1
Name: encryptJS
Version: 0.0.2
Summary: 一个简易工具提供常见加密解密功能如MD5,AES,SHA1等
Home-page: 
Download-URL: 
Author: jinmingzhou
Author-email: 17816765317@163.com
Requires-Python: >=3.10
Requires-Dist: PyExecJS2>=1.6.1
Requires-Dist: requests
Requires-Dist: pycryptodome
Requires-Dist: gmssl
Requires-Dist: cryptography
